L_bash_profile.py
L_bash_profile-0.1.4.dist-info/LICENSE.txt
L_bash_profile-0.1.4.dist-info/METADATA
L_bash_profile-0.1.4.dist-info/WHEEL
L_bash_profile-0.1.4.dist-info/entry_points.txt
L_bash_profile-0.1.4.dist-info/top_level.txt
L_bash_profile-0.1.4.dist-info/RECORD
