Metadata-Version: 2.1
Name: L_bash_profile
Version: 0.1.4
Summary: Profile the execution speed of Bash script
Author-email: Kamil Cukrowski <kamilcukrowski@gmail.com>
Maintainer-email: Kamil Cukrowski <kamilcukrowski@gmail.com>
License:                     GNU GENERAL PUBLIC LICENSE
Project-URL: Homepage, https://github.com/kamilcuk/L_bash_profile
Project-URL: Bug Reports, https://github.com/kamilcuk/L_bash_profile/issues
Project-URL: Source, https://github.com/kamilcuk/L_bash_profile/
Keywords: bash,profile,development
Requires-Python: >=3.9
License-File: LICENSE.txt
Requires-Dist: graphviz
Requires-Dist: tabulate
Requires-Dist: click
Requires-Dist: clickdc
Provides-Extra: test
Requires-Dist: pytest; extra == "test"
